README
flask_socialshare.py
setup.py
Flask_SocialShare.egg-info/PKG-INFO
Flask_SocialShare.egg-info/SOURCES.txt
Flask_SocialShare.egg-info/dependency_links.txt
Flask_SocialShare.egg-info/not-zip-safe
Flask_SocialShare.egg-info/requires.txt
Flask_SocialShare.egg-info/top_level.txt