Metadata-Version: 1.0
Name: Flask-SocialShare
Version: 0.0.1
Summary: Flask social sharing helpers
Home-page: UNKNOWN
Author: Paul d'Hubert
Author-email: contact@pauldhubert.com
License: BSD
Platform: any
